{
    "id": "so-mi-ro-mooc-dong-lanh-thaco-ctsv-3dde4500",
    "name": "Sơ mi rơ moóc đông lạnh THACO CTSV/3DDE4500 45 Feet 30 tấn",
    "slug": "so-mi-ro-mooc-dong-lanh-thaco-ctsv-3dde4500",
    "brand": "THACO",
    "model": "CTSV/3DDE4500",
    "type": "mooc",
    "price": null,
    "priceText": "Liên hệ",
    "weightText": "Tải trọng 30.200 kg",
    "weight": 30.2,
    "length": 14.07,
    "width": 2.5,
    "height": 4.0,
    "dimensions": "14.070 × 2.500 × 4.000 mm",
    "insideDimension": "13.590 × 2.350 × 2.350 mm",
    "thumbnailUrl": "https://images.unsplash.com/photo-1558618047-f2c57e73c83c?w=800&h=600&fit=crop",
    "images": [
        "https://images.unsplash.com/photo-1558618047-f2c57e73c83c?w=800&h=600&fit=crop"
    ],
    "origin": "Việt Nam (Máy lạnh Thermo King - Mỹ)",
    "isNew": true,
    "isHot": true,
    "stockStatus": "in-stock",
    "description": "Sơ mi rơ moóc đông lạnh THACO CTSV/3DDE4500 45 Feet - Máy lạnh Thermo King SLXi-400, tải trọng dẫn đầu 30.200 kg, chiều dài thùng 13.6m, treo cơ khí nhíp 2 tầng, phanh khí nén 2 dòng, thùng Composite cách nhiệt PU dày.",
    "detailedDescription": "<h2>Sơ Mi Rơ Moóc Đông Lạnh THACO CTSV/3DDE4500: Đỉnh Cao Tải Trọng Phân Khúc 45 Feet</h2><p>Đối với các tuyến vận tải đường dài xuyên Việt hoặc xuất khẩu tiểu ngạch sang Trung Quốc, mẫu <strong>Sơ mi rơ moóc đông lạnh THACO CTSV/3DDE4500</strong> là sự lựa chọn ưu tiên hàng đầu trong giai đoạn 2025-2026. Với kích thước chiều dài lên đến <strong>14m (45 feet)</strong>, sản phẩm này được thiết kế để tối đa hóa không gian chứa hàng và tải trọng vận chuyển.</p><h3>Kích Thước Khủng Và Tải Trọng Dẫn Đầu</h3><p>THACO CTSV sở hữu <strong>tải trọng cho phép chở lên đến 30.200 kg</strong> - mức cao nhất trong phân khúc moóc đông lạnh hiện nay:</p><ul><li><strong>Chiều dài lòng thùng:</strong> 13.6m - xếp được nhiều pallet nhất</li><li><strong>Giảm chi phí vận chuyển:</strong> Nhiều hàng hơn mỗi chuyến</li><li><strong>Tăng lợi nhuận:</strong> Tối ưu chi phí trên mỗi đơn vị sản phẩm</li><li><strong>Phù hợp:</strong> Vận tải đường dài xuyên Việt, xuất khẩu tiểu ngạch</li></ul><h3>Máy Lạnh Thermo King SLXi-400 Thế Hệ Mới</h3><p>Xe được trang bị dòng <strong>máy lạnh Thermo King SLXi-400</strong> - tiêu chuẩn toàn cầu về vận tải lạnh:</p><ul><li><strong>Hạ nhiệt siêu tốc:</strong> Đạt nhiệt độ yêu cầu nhanh chóng</li><li><strong>Độ bền bỉ cực cao:</strong> Vận hành liên tục không lo hỏng hóc</li><li><strong>Công nghệ xanh:</strong> Tiết kiệm nhiên liệu đáng kể</li><li><strong>Điều khiển thông minh:</strong> Ghi chép và trích xuất dữ liệu nhiệt độ hành trình</li><li><strong>Đáp ứng tiêu chuẩn:</strong> Ngành thực phẩm và dược phẩm khắt khe</li></ul><h3>Kết Cấu Chịu Lực Và Độ Bền Cao</h3><ul><li><strong>Dầm chính:</strong> Thép hợp kim cường lực cao, dập hình bằng máy ép lớn</li><li><strong>Không võng:</strong> Chở đầy tải lâu ngày vẫn giữ nguyên hình dạng</li><li><strong>Xử lý bề mặt:</strong> Sơn tĩnh điện (ED) chống ăn mòn</li><li><strong>Bảo vệ:</strong> Chống hơi ẩm và muối biển suốt vòng đời</li></ul><h3>Hệ Thống Treo Cơ Khí Nhíp 2 Tầng</h3><ul><li><strong>Loại treo:</strong> Treo cơ khí, nhíp lá 2 tầng chịu tải</li><li><strong>Trục:</strong> 03 trục chịu tải cao (13 tấn/trục)</li><li><strong>Độ bền:</strong> Chịu được tải trọng lớn dài hạn</li><li><strong>Bảo dưỡng:</strong> Đơn giản, chi phí thấp</li></ul><h3>Hệ Thống Phanh An Toàn</h3><ul><li><strong>Phanh khí nén 2 dòng:</strong> Tác động cả 3 trục đồng thời</li><li><strong>Hiệu suất cao:</strong> Dừng xe nhanh và an toàn</li><li><strong>Lốp 11R22.5 hoặc 12R22.5:</strong> Không săm, bền bỉ</li></ul><h3>Thùng Composite Cách Nhiệt Cao Cấp</h3><ul><li><strong>Vật liệu:</strong> Composite cao cấp mặt phẳng</li><li><strong>Cách nhiệt:</strong> Foam PU dày, giữ lạnh tốt</li><li><strong>Độ kín:</strong> Không để thoát nhiệt, tiết kiệm năng lượng</li><li><strong>Vệ sinh:</strong> Dễ dàng lau chùi, đạt chuẩn ATTP</li></ul><h3>Ứng Dụng Vận Chuyển</h3><ul><li>Vận tải đường dài xuyên Việt Bắc-Nam</li><li>Xuất khẩu tiểu ngạch sang Trung Quốc</li><li>Thực phẩm đông lạnh quy mô lớn</li><li>Hàng hóa cần bảo quản lạnh số lượng nhiều</li><li>Logistics chuỗi cung ứng lạnh chuyên nghiệp</li></ul><h3>Tại Sao Chọn THACO CTSV/3DDE4500?</h3><ul><li><strong>Tải trọng cao nhất:</strong> 30.200 kg - dẫn đầu phân khúc 45 feet</li><li><strong>Thùng dài nhất:</strong> 13.6m - xếp được nhiều pallet nhất</li><li><strong>Máy lạnh Thermo King:</strong> Tiêu chuẩn toàn cầu, độ tin cậy cao</li><li><strong>Kết cấu bền bỉ:</strong> Thép cường lực, sơn ED chống ăn mòn</li><li><strong>Thương hiệu THACO:</strong> Nhà sản xuất ô tô lớn nhất Việt Nam</li></ul>",
    "features": [
        "Tải trọng dẫn đầu 30.200 kg - cao nhất phân khúc 45 feet",
        "Chiều dài thùng 13.6m xếp được nhiều pallet nhất",
        "Máy lạnh Thermo King SLXi-400 tiêu chuẩn toàn cầu",
        "Dầm chính thép hợp kim cường lực cao",
        "Khung gầm sơn tĩnh điện ED chống ăn mòn",
        "Treo cơ khí nhíp 2 tầng chịu tải cao",
        "Phanh khí nén 2 dòng tác động 3 trục",
        "Thùng Composite cách nhiệt Foam PU dày",
        "Chốt kéo KZ1012 chịu lực kéo lớn"
    ],
    "trailerType": "đông-lạnh",
    "kerbWeight": "8.800 kg",
    "grossWeight": "39.000 kg",
    "refrigerationUnit": "Thermo King SLXi-400",
    "trailerSpec": {
        "dimensions": {
            "overallDimensions": "14.070 × 2.500 × 4.000 mm",
            "containerDimensions": "13.590 × 2.350 × 2.350 mm",
            "containerLength": "45 Feet (13.6m)"
        },
        "weight": {
            "curbWeight": "8.800 kg",
            "payload": "Tải trọng 30.200 kg",
            "grossWeight": "39.000 kg"
        },
        "chassis": {
            "mainBeam": "Thép hợp kim cường lực cao, dập hình máy ép",
            "surfaceTreatment": "Sơn tĩnh điện (ED) chống ăn mòn",
            "landingGear": "Tay quay 2 tốc độ (Tải trọng 28-80 tấn)",
            "kingpin": "Model KZ1012, chịu lực kéo lớn"
        },
        "axleAndSuspension": {
            "axleType": "Trục chịu tải cao 13 tấn",
            "axleCount": 3,
            "suspensionType": "Treo cơ khí, nhíp lá 2 tầng chịu tải",
            "tireSpec": "11R22.5 hoặc 12R22.5 (Không săm)"
        },
        "systems": {
            "brakeSystem": "Phanh khí nén 2 dòng, tác động 3 trục",
            "refrigerationUnit": "Thermo King SLXi-400"
        },
        "body": {
            "material": "Composite cao cấp mặt phẳng",
            "insulation": "Cách nhiệt Foam PU dày"
        }
    },
    "order": 11
}